{
    "QUESTION_1": {
      "id": 1,
      "body": "What do you value more in a workplace, consistency or potential for growth?",
      "options": [
        "Strongly Disagree",
        "Disagree",
        "Neutral",
        "Agree",
        "Strongly Agree"
      ]
    },
    "QUESTION_2": {
      "id": 2,
      "body": "Are you willing to put in extra hours for the sake of promotion?",
      "options": [
        "Strongly Disagree",
        "Disagree",
        "Neutral",
        "Agree",
        "Strongly Agree"
      ]
    },
    "QUESTION_3": {
      "id": 3,
      "body": "How important is work-life balance to you?",
      "options": [
        "Strongly Disagree",
        "Disagree",
        "Neutral",
        "Agree",
        "Strongly Agree"
      ]
    },
    "QUESTION_4": {
      "id": 4,
      "body": "How do your personal ethics influence your job choices?",
      "options": [
        "Strongly Disagree",
        "Disagree",
        "Neutral",
        "Agree",
        "Strongly Agree"
      ]
    },
    "QUESTION_5": {
      "id": 5,
      "body": "Are you more of a group collaborator or an independent worker?",
      "options": [
        "Strongly Disagree",
        "Disagree",
        "Neutral",
        "Agree",
        "Strongly Agree"
      ]
    },
    "QUESTION_6": {
      "id": 6,
      "body": "What kind of workspace do you prefer?",
      "options": [
        "Strongly Disagree",
        "Disagree",
        "Neutral",
        "Agree",
        "Strongly Agree"
      ]
    },
    "QUESTION_7": {
      "id": 7,
      "body": "Do you think of your future career as a way to realize your best self, or an avenue to make money?",
      "options": [
        "Strongly Disagree",
        "Disagree",
        "Neutral",
        "Agree",
        "Strongly Agree"
      ]
    }
  }  